fastapi_docshield/__init__.py
fastapi_docshield/docshield.py
fastapi_docshield/static_handler.py
fastapi_docshield/static/redoc/redoc.standalone.js
fastapi_docshield/static/swagger/swagger-ui-bundle.js
fastapi_docshield/static/swagger/swagger-ui.css
fastapi_docshield-0.2.1.dist-info/METADATA
fastapi_docshield-0.2.1.dist-info/WHEEL
fastapi_docshield-0.2.1.dist-info/licenses/LICENSE
fastapi_docshield-0.2.1.dist-info/RECORD
