Metadata-Version: 2.4
Name: fastapi-docshield
Version: 0.2.1
Summary: A simple FastAPI integration to protect documentation endpoints with authentication
Project-URL: Homepage, https://github.com/georgekhananaev/fastapi-docshield
Project-URL: Bug Tracker, https://github.com/georgekhananaev/fastapi-docshield/issues
Project-URL: Documentation, https://github.com/georgekhananaev/fastapi-docshield#readme
Project-URL: Source Code, https://github.com/georgekhananaev/fastapi-docshield
Author-email: George Khananaev <georgekhananaev@gmail.com>
License: MIT License
License-File: LICENSE
Keywords: authentication,documentation,fastapi,security
Classifier: Development Status :: 4 - Beta
Classifier: Intended Audience :: Developers
Classifier: License :: OSI Approved :: MIT License
Classifier: Operating System :: OS Independent
Classifier: Programming Language :: Python :: 3
Classifier: Programming Language :: Python :: 3.7
Classifier: Programming Language :: Python :: 3.8
Classifier: Programming Language :: Python :: 3.9
Classifier: Programming Language :: Python :: 3.10
Classifier: Programming Language :: Python :: 3.11
Classifier: Programming Language :: Python :: 3.12
Classifier: Programming Language :: Python :: 3.13
Classifier: Topic :: Internet :: WWW/HTTP :: HTTP Servers
Classifier: Topic :: Software Development :: Libraries :: Python Modules
Requires-Python: >=3.7
Requires-Dist: fastapi>=0.68.0
Requires-Dist: requests>=2.31.0
Requires-Dist: uvicorn>=0.22.0
Provides-Extra: dev
Requires-Dist: httpx>=0.23.0; extra == 'dev'
Requires-Dist: pytest-cov>=4.0.0; extra == 'dev'
Requires-Dist: pytest>=7.0.0; extra == 'dev'
Requires-Dist: python-multipart>=0.0.5; extra == 'dev'
Requires-Dist: requests>=2.28.0; extra == 'dev'
Requires-Dist: uvicorn>=0.18.0; extra == 'dev'
